mcp_aruba/__init__.py
mcp_aruba/calendar_client.py
mcp_aruba/email_client.py
mcp_aruba/server.py
mcp_aruba/signature.py
mcp_aruba-0.2.1.dist-info/METADATA
mcp_aruba-0.2.1.dist-info/WHEEL
mcp_aruba-0.2.1.dist-info/entry_points.txt
mcp_aruba-0.2.1.dist-info/licenses/LICENSE
mcp_aruba-0.2.1.dist-info/RECORD
