Metadata-Version: 2.4
Name: mcp-aruba
Version: 0.2.1
Summary: MCP server for Aruba email and calendar via IMAP/SMTP/CalDAV
Project-URL: Homepage, https://github.com/jackfioru92/mcp-aruba-email
Project-URL: Repository, https://github.com/jackfioru92/mcp-aruba-email
Project-URL: Issues, https://github.com/jackfioru92/mcp-aruba-email/issues
Author-email: Giacomo Fiorucci <giacomo.fiorucci@emotion-team.com>
License-File: LICENSE
Requires-Python: >=3.10
Requires-Dist: caldav>=1.3.9
Requires-Dist: icalendar>=5.0.0
Requires-Dist: mcp[cli]>=1.2.0
Requires-Dist: python-dotenv>=1.0.0
Provides-Extra: dev
Requires-Dist: pytest-asyncio>=0.23.0; extra == 'dev'
Requires-Dist: pytest>=7.0.0; extra == 'dev'
